PytorchRengongzhinengJichuzhishiChuyi/README.md
PytorchRengongzhinengJichuzhishiChuyi/__init__.py
PytorchRengongzhinengJichuzhishiChuyi/__main__.py
PytorchRengongzhinengJichuzhishiChuyi/file.epub
PytorchRengongzhinengJichuzhishiChuyi/index.html
PytorchRengongzhinengJichuzhishiChuyi/css/__init__.py
PytorchRengongzhinengJichuzhishiChuyi/css/annotations.css
PytorchRengongzhinengJichuzhishiChuyi/css/main.css
PytorchRengongzhinengJichuzhishiChuyi/css/normalize.css
PytorchRengongzhinengJichuzhishiChuyi/css/popup.css
PytorchRengongzhinengJichuzhishiChuyi/font/__init__.py
PytorchRengongzhinengJichuzhishiChuyi/font/fontello.eot
PytorchRengongzhinengJichuzhishiChuyi/font/fontello.svg
PytorchRengongzhinengJichuzhishiChuyi/font/fontello.ttf
PytorchRengongzhinengJichuzhishiChuyi/font/fontello.woff
PytorchRengongzhinengJichuzhishiChuyi/img/__init__.py
PytorchRengongzhinengJichuzhishiChuyi/img/annotator-glyph-sprite.png
PytorchRengongzhinengJichuzhishiChuyi/img/annotator-icon-sprite.png
PytorchRengongzhinengJichuzhishiChuyi/img/apple-touch-icon.png
PytorchRengongzhinengJichuzhishiChuyi/img/cancelfullscreen.png
PytorchRengongzhinengJichuzhishiChuyi/img/close.png
PytorchRengongzhinengJichuzhishiChuyi/img/fullscreen.png
PytorchRengongzhinengJichuzhishiChuyi/img/loader.gif
PytorchRengongzhinengJichuzhishiChuyi/img/menu-icon.png
PytorchRengongzhinengJichuzhishiChuyi/img/save.png
PytorchRengongzhinengJichuzhishiChuyi/img/saved.png
PytorchRengongzhinengJichuzhishiChuyi/img/settings-s.png
PytorchRengongzhinengJichuzhishiChuyi/img/settings.png
PytorchRengongzhinengJichuzhishiChuyi/img/star.png
PytorchRengongzhinengJichuzhishiChuyi/js/__init__.py
PytorchRengongzhinengJichuzhishiChuyi/js/epub.js
PytorchRengongzhinengJichuzhishiChuyi/js/epub.min.js
PytorchRengongzhinengJichuzhishiChuyi/js/epub.min.map
PytorchRengongzhinengJichuzhishiChuyi/js/hooks.min.js
PytorchRengongzhinengJichuzhishiChuyi/js/hooks.min.map
PytorchRengongzhinengJichuzhishiChuyi/js/reader.js
pytorch_rengongzhineng_jichuzhishi_chuyi-2024.3.6.0.dist-info/METADATA
pytorch_rengongzhineng_jichuzhishi_chuyi-2024.3.6.0.dist-info/WHEEL
pytorch_rengongzhineng_jichuzhishi_chuyi-2024.3.6.0.dist-info/entry_points.txt
pytorch_rengongzhineng_jichuzhishi_chuyi-2024.3.6.0.dist-info/top_level.txt
pytorch_rengongzhineng_jichuzhishi_chuyi-2024.3.6.0.dist-info/RECORD
